[
    [
        {
            "Link": {
                "url": "https://www.angelsport.de/zielfisch/karpfenangeln/karpfenruten/",
                "pos": "3"
            }
        },
        {
            "Affiliate Links": 0
        },
        {
            "Durschnittliche Hervorhebungsstaerke": 0
        },
        {
            "Durschnittliche Position": 0
        },
        {
            "Score": 0
        },
        {
            "textLength": 38780
        },
        {
            "relScore": 0.0
        }
    ],
    []
]