[
    [
        {
            "Link": {
                "url": "https://www.weltbild.de/geschenke/muttertagsgeschenke",
                "pos": "8"
            }
        },
        {
            "Affiliate Links": 0
        },
        {
            "Durschnittliche Hervorhebungsstaerke": 0
        },
        {
            "Durschnittliche Position": 0
        },
        {
            "Score": 0
        },
        {
            "textLength": 26236
        },
        {
            "relScore": 0.0
        }
    ],
    []
]