[
    [
        {
            "Link": {
                "url": "https://deutschlandtest.de/rankings/beste-haushaltsgeraete",
                "pos": "5"
            }
        },
        {
            "Affiliate Links": 0
        },
        {
            "Durschnittliche Hervorhebungsstaerke": 0
        },
        {
            "Durschnittliche Position": 0
        },
        {
            "Score": 0
        },
        {
            "textLength": 27026
        },
        {
            "relScore": 0.0
        }
    ],
    []
]