[
    [
        {
            "Link": {
                "url": "https://www.neff-home.com/de/neff-entdecken/neff-die-marke/stiftung-warentest-uebersicht",
                "pos": "13"
            }
        },
        {
            "Affiliate Links": 0
        },
        {
            "Durschnittliche Hervorhebungsstaerke": 0
        },
        {
            "Durschnittliche Position": 0
        },
        {
            "Score": 0
        },
        {
            "textLength": 21588
        },
        {
            "relScore": 0.0
        }
    ],
    []
]